{
  "Q1a": {
    "volkswagen": "VW",
    "volks wagon": "VW",
    "volkswagon": "VW",
    "vw": "VW",
    "cadillc": "Cadillac",
    "caddilac": "Cadillac",
    "Alfa romeo":"Alfa Romeo",
    "Alla Romeo":"Alfa Romeo",
    "alfa romeo ":"Alfa Romeo",
    "Ibrida":"Alfa Romeo",
    "alfaromeo":"Alfa Romeo",
    "AUDI":"Audi",
    "Audi Q2":"Audi",
    "Audi a1":"Audi",
    "Audi a4":"Audi",
    "Audi a2":"Audi",
    "BMW":"BMW",
    "Bmw x2":"BMW",
    "BWM":"BMW",
    "BMW M3":"BMW",
    "Bmw m4":"BMW",
    "BMW 525li":"BMW",
    "BMW A3":"BMW",
    "BMW m5":"BMW",
    "Bmv":"BMW",
    "BMX":"BMW",
    "Benz Cadillac":"Cadillac",
    "cadillac":"Cadillac",
    "Chevrolet":"Chevrolet",
    "Chervolet":"Chevrolet",
    "Chrysler":"Chrysler",
    "citroen":"Citroen",
    "Citroën c5 aircross":"Citroen",
    "Citroën":"Citroen",
    "Xsara HDi Citroën":"Citroen",
    "C3":"Citroen",
    "Citroen c5":"Citroen",
    "Citroen C1":"Citroen",
    "citreon":"Citroen",
    "saxo":"Citroen",
    "Citrien":"Citroen",
    "Citr√¥en":"Citroen",
    "dacia":"Dacia",
    "Dacia sandero":"Dacia",
    "Dacia duster":"Dacia",
    "Daccia":"Dacia",
    "Stapway":"Dacia",
    "Duster":"Dacia",
    "Daewoo":"Daewoo",
    "Daihatsu":"Daihatsu",
    "Dodge":"Dodge",
    "Fiat":"Fiat",
    "Fiat panda":"Fiat",
    "Fiat 500":"Fiat",
    "Fiat punto":"Fiat",
    "500":"Fiat",
    "Panda":"Fiat",
    "Punto":"Fiat",
    "Ford":"Ford",
    "FORD FIESTA":"Ford",
    "Ford focus":"Ford",
    "Ford Puma":"Ford",
    "Ford estate":"Ford",
    "ford explorer":"Ford",
    "Ford EcoSport":"Ford",
    "Ford c max":"Ford",
    "Fiesta":"Ford",
    "Ford escort":"Ford",
    "Ford s max":"Ford",
    "Ford ka":"Ford",
    "Focus":"Ford",
    "Ford mondeo":"Ford",
    "Ford kia":"Ford",
    "Mondeo":"Ford",
    "Ford Ranger":"Ford",
    "FORD ESPORT":"Ford",
    "Ford fiat":"Ford",
    "Honda accord":"Honda",
    "Honda":"Honda",
    "Honda civic":"Honda",
    "Honda insight":"Honda",
    " Honda HR-V ":"Honda",
    "Honda pilot":"Honda",
    "Hummer":"Hummer",
    "Hyundai":"Hyundai",
    "Hyundai tucson":"Hyundai",
    "Hyundal":"Hyundai",
    "Hyundai Sonata":"Hyundai",
    "Hyundai Ioniq":"Hyundai",
    "Hyundai kona":"Hyundai",
    "Hyundai i10":"Hyundai",
    "Hyundai i30":"Hyundai",
    "Hiyundai":"Hyundai",
    "Infiniti":"Infiniti",
    "Infinity":"Infiniti",
    "Isuzu":"Isuzu",
    "Jaguar":"Jaguar",
    "Jeep":"Jeep",
    "Kia":"Kia",
    "Kia Sorento":"Kia",
    "Kia K5":"Kia",
    "Ka":"Kia",
    "Kia ev3":"Kia",
    "Lada":"Lada",
    "lancia":"Lancia",
    "LANDROVER":"Land Rover",
    "Land Rover":"Land Rover",
    "Land rover discovery":"Land Rover",
    "Lexus":"Lexus",
    "lexus 350":"Lexus",
    "Lexus ":"Lexus",
    "Lexus Rx 350":"Lexus",
    "Mazda":"Mazda",
    "mazda3":"Mazda",
    "Mazda 6":"Mazda",
    "Mazda 2":"Mazda",
    "Mazda CX-5":"Mazda",
    "Mercedes":"Mercedes",
    "Mercedes Benz":"Mercedes",
    "Mercedes-Benz":"Mercedes",
    "Mercedes Benz E class":"Mercedes",
    "GLE":"Mercedes",
    "BENZ":"Mercedes",
    "Mercedez":"Mercedes",
    "mercedes bentz":"Mercedes",
    "Mercedes S series":"Mercedes",
    "Mercedes - Benz":"Mercedes",
    "Mercedes-Benz E300":"Mercedes",
    "Mercedes Benz GLE 350":"Mercedes",
    "Mercedes- Benz":"Mercedes",
    "Mercedes Benz C class":"Mercedes",
    "Mercedes Benz 4Matic":"Mercedes",
    "Mercedes-Benz.":"Mercedes",
    "merc√®d√®s":"Mercedes",
    "Mercdes":"Mercedes",
    "Mg":"MG Rover",
    "Mg3":"MG Rover",
    "mini cooper":"MINI",
    "Mini":"MINI",
    "Mini Cooper countryman":"MINI",
    "Mimi":"MINI",
    "Mini Hatch":"MINI",
    "Mitsubishi":"Mitsubishi",
    "mitsubshi":"Mitsubishi",
    "Nissan":"Nissan",
    "Nissan quashquai":"Nissan",
    "Nissan juke":"Nissan",
    "Nissan Altima":"Nissan",
    "Nisan":"Nissan",
    "Nissan Micra":"Nissan",
    "Nissan duke":"Nissan",
    "Nissan amanda":"Nissan",
    "Nissan qashqai":"Nissan",
    "Opel":"Opel/Vauxhall",
    "Vauxhall":"Opel/Vauxhall",
    "Vauxhall corsa":"Opel/Vauxhall",
    "Corsa":"Opel/Vauxhall",
    "Opel calibra":"Opel/Vauxhall",
    "antara":"Opel/Vauxhall",
    "Opel Mocca":"Opel/Vauxhall",
    "Moka":"Opel/Vauxhall",
    "Vauxhall astra":"Opel/Vauxhall",
    "Crosslander":"Opel/Vauxhall",
    "Vauxhall Adam":"Opel/Vauxhall",
    "opel Astra":"Opel/Vauxhall",
    "Opei":"Opel/Vauxhall",
    "Vauxhall cora":"Opel/Vauxhall",
    "Vauxhull":"Opel/Vauxhall",
    "Vauxhall crossland":"Opel/Vauxhall",
    "Vauxhall mokka":"Opel/Vauxhall",
    "Opel Corsa":"Opel/Vauxhall",
    "Vauxhall grand land":"Opel/Vauxhall",
    "vauxhaull":"Opel/Vauxhall",
    "Opel.":"Opel/Vauxhall",
    "peugeot":"Peugeot",
    "Peugeot 206":"Peugeot",
    "Peugeot 3008":"Peugeot",
    "Peugeot 107":"Peugeot",
    "Peugeot 308":"Peugeot",
    "Peugeo":"Peugeot",
    "Peugeot 4008":"Peugeot",
    "Peugeot rifter":"Peugeot",
    "Peugeot 307":"Peugeot",
    "Peugeot 208":"Peugeot",
    "Pegeout":"Peugeot",
    "Peugeot electric":"Peugeot",
    "Peuguot":"Peugeot",
    "peuegot":"Peugeot",
    "Pegueot":"Peugeot",
    "Peigeot":"Peugeot",
    "Porsche":"Porsche",
    "Porshe":"Porsche",
    "Renault":"Renault",
    "Clio":"Renault",
    "Renault clio":"Renault",
    "Renault e4":"Renault",
    "Renault kaptor":"Renault",
    "Kangoo":"Renault",
    "Renault 5":"Renault",
    "Twingo":"Renault",
    "Megane":"Renault",
    "Laguna":"Renault",
    "Renault Captur":"Renault",
    "Renault Twingo":"Renault",
    "Saab":"Saab",
    "Seat":"Seat",
    "Ibiza":"Seat",
    "SEAT leon":"Seat",
    "Seat ibiza":"Seat",
    "Seat arona":"Seat",
    "Skoda":"Skoda",
    "Skoda fabia":"Skoda",
    "Skoda Karoq":"Skoda",
    "Skoda kamiq":"Skoda",
    "Skoda Octavia":"Skoda",
    "Skoda Supreme":"Skoda",
    "Ssangyong":"Ssangyong",
    "Subaru":"Subaru",
    "Suzuki":"Suzuki",
    "Toyota":"Toyota",
    "Toyota corola":"Toyota",
    "toyota hilander":"Toyota",
    "Toyota Spider":"Toyota",
    "Fortuna":"Toyota",
    "toyota yaris":"Toyota",
    "Yaris":"Toyota",
    "Toyota Camry":"Toyota",
    "Camry":"Toyota",
    "Corrola":"Toyota",
    "Toyota iq":"Toyota",
    "Toyota corolla":"Toyota",
    "Touran":"Toyota",
    "Venza":"Toyota",
    "Sienna":"Toyota",
    "Corolla":"Toyota",
    "Toyota Sienna":"Toyota",
    "Auris":"Toyota",
    "Toyota Tacoma":"Toyota",
    "Highlander":"Toyota",
    "Volvo":"Volvo",
    "Volco":"Volvo",
    "Volwo":"Volvo",
    "volkswagen":"VW",
    "VW":"VW",
    "Volkswagen Golf":"VW",
    "Golf":"VW",
    "Polo":"VW",
    "VIVO":"VW",
    "VW Golf":"VW",
    "Volkwagen polo":"VW",
    "Volkwagon golf":"VW",
    "volksxagen":"VW",
    "VW Polo":"VW",
    "beetle":"VW",
    "Volkswagen Polo":"VW",
    "Turan":"VW",
    "VOKSWAGEN":"VW",
    "Aston Martin":"Aston Martin",
    "Lotus":"Lotus",
    "Range rover":"Range Rover",
    "rangerover":"Range Rover",
    "Rang rover":"Range Rover",
    "Ranger Rover":"Range Rover",
    "Rover":"Rover",
    "smart":"Smart",
    "Trabant":"Trabant",
    "Ferrari":"Ferrari",
    "Ferarri":"Ferrari",
    "Lamborghini":"Lamborghini",
    "Lamborghini urus":"Lamborghini",
    "Lamborgini":"Lamborghini",
    "Maserati":"Maserati",
    "Masarati":"Maserati",
    "Bentley":"Bentley",
    "Gm":"General Motors",
    "Rolls Royce":"Rolls Royce",
    "Tata":"Tata",
    "Tesla":"Tesla",
    "Telsa":"Tesla",
    "Bugatti":"Bugatti",
    "Ds":"DS",
    "Ds7":"DS",
    "Cupra":"Cupra",
    "polestar":"Polestar",
    "Byd":"BYD",
    "acura":"Acura",
    "Acura TSX":"Acura",
    "Omoda":"Omoda",
    "Dr":"DR",
    "Maybach":"Other",
    "Torregrosa":"Other",
    "Nio":"Other",
    "Alpine":"Other",
    "Simca":"Other",
    "Genesis":"Other",
    "iveco":"Other",
    "Van":"Other",
    "Evo":"Other",
    "Arbarth":"Other",
    "SUV":"Other",
    "Austin":"Other",
    "Abarth":"Other",
    "Mclaren":"Other",
    "Dolphin":"Other",
    "Lakaka":"Other",
    "DFM":"Other",
    "Linux":"Other",
    "Labarth":"Other",
    "amg":"Other",
    "nimax":"Other",
    "Link and co":"Other",
    "Hellcat":"Other",
    "link&co":"Other",
    "Mc Lauren":"Other",
  },
  "f3": {}
}

